soda_ftp_download/__init__.py
soda_ftp_download/__main__.py
soda_ftp_download/download_file_m.py
soda_ftp_download/main.py
soda_ftp_download-2025.5.17.0.dist-info/METADATA
soda_ftp_download-2025.5.17.0.dist-info/WHEEL
soda_ftp_download-2025.5.17.0.dist-info/entry_points.txt
soda_ftp_download-2025.5.17.0.dist-info/licenses/LICENSE
soda_ftp_download-2025.5.17.0.dist-info/RECORD
