Metadata-Version: 2.4
Name: soda-ftp-download
Version: 2025.5.17.0
Summary: download files from FTP with progress bar and auto-resume support.
Project-URL: Repository, https://github.com/soda92/soda-ftp-download
License-File: LICENSE
Requires-Python: >=3.10
Requires-Dist: tqdm>=4.67.1
